visions/__init__.py
visions/declarative.py
visions/functional.py
visions/py.typed
visions/backends/__init__.py
visions/backends/numpy/__init__.py
visions/backends/numpy/array_utils.py
visions/backends/numpy/sequences.py
visions/backends/numpy/test_utils.py
visions/backends/numpy/types/__init__.py
visions/backends/numpy/types/boolean.py
visions/backends/numpy/types/complex.py
visions/backends/numpy/types/date_time.py
visions/backends/numpy/types/float.py
visions/backends/numpy/types/integer.py
visions/backends/numpy/types/object.py
visions/backends/numpy/types/string.py
visions/backends/numpy/types/time_delta.py
visions/backends/pandas/__init__.py
visions/backends/pandas/sequences.py
visions/backends/pandas/series_utils.py
visions/backends/pandas/test_utils.py
visions/backends/pandas/traversal.py
visions/backends/pandas/types/__init__.py
visions/backends/pandas/types/boolean.py
visions/backends/pandas/types/categorical.py
visions/backends/pandas/types/complex.py
visions/backends/pandas/types/count.py
visions/backends/pandas/types/date.py
visions/backends/pandas/types/date_time.py
visions/backends/pandas/types/email_address.py
visions/backends/pandas/types/file.py
visions/backends/pandas/types/float.py
visions/backends/pandas/types/geometry.py
visions/backends/pandas/types/image.py
visions/backends/pandas/types/integer.py
visions/backends/pandas/types/ip_address.py
visions/backends/pandas/types/numeric.py
visions/backends/pandas/types/object.py
visions/backends/pandas/types/ordinal.py
visions/backends/pandas/types/path.py
visions/backends/pandas/types/sparse.py
visions/backends/pandas/types/string.py
visions/backends/pandas/types/time.py
visions/backends/pandas/types/time_delta.py
visions/backends/pandas/types/url.py
visions/backends/pandas/types/uuid.py
visions/backends/python/__init__.py
visions/backends/python/sequences.py
visions/backends/python/series_utils.py
visions/backends/python/types/__init__.py
visions/backends/python/types/boolean.py
visions-0.8.0.dist-info/LICENSE
visions-0.8.0.dist-info/METADATA
visions-0.8.0.dist-info/WHEEL
visions-0.8.0.dist-info/top_level.txt
visions-0.8.0.dist-info/RECORD
