Metadata-Version: 2.2
Name: visions
Version: 0.8.0
Summary: Visions
Author-email: Dylan Profiler <visions@ictopzee.nl>
License: BSD License
Project-URL: Repository, https://github.com/dylan-profiler/visions
Project-URL: Documentation, https://dylan-profiler.github.io/visions
Classifier: Programming Language :: Python :: 3
Classifier: Programming Language :: Python :: 3.9
Classifier: Programming Language :: Python :: 3.10
Classifier: Programming Language :: Python :: 3.11
Classifier: Programming Language :: Python :: 3.12
Classifier: Programming Language :: Python :: 3.13
Requires-Python: >=3.8
License-File: LICENSE
Requires-Dist: numpy>=1.23.2
Requires-Dist: pandas>=2.0.0
Requires-Dist: attrs>=19.3.0
Requires-Dist: networkx>=2.4
Requires-Dist: multimethod>=1.4
Requires-Dist: puremagic
Provides-Extra: type-geometry
Requires-Dist: shapely; extra == "type-geometry"
Provides-Extra: type-image-path
Requires-Dist: imagehash; extra == "type-image-path"
Requires-Dist: Pillow; extra == "type-image-path"
Requires-Dist: puremagic; extra == "type-image-path"
Provides-Extra: plotting
Requires-Dist: pydot; extra == "plotting"
Requires-Dist: pygraphviz; extra == "plotting"
Requires-Dist: matplotlib; extra == "plotting"
Provides-Extra: testing
Requires-Dist: visions[type_geometry,type_image_path]; extra == "testing"
Requires-Dist: setuptools>=46.1.3; extra == "testing"
Requires-Dist: wheel>=0.34.2; extra == "testing"
Requires-Dist: black>=20.8b1; extra == "testing"
Requires-Dist: isort>=5.0.9; extra == "testing"
Requires-Dist: mypy>=0.770; extra == "testing"
Requires-Dist: recommonmark>=0.6.0; extra == "testing"
Requires-Dist: nbsphinx; extra == "testing"
Requires-Dist: sphinx_rtd_theme>=0.4.3; extra == "testing"
Requires-Dist: sphinx-autodoc-typehints>=1.10.3; extra == "testing"
Requires-Dist: IPython; extra == "testing"
Requires-Dist: Sphinx-copybutton; extra == "testing"
Requires-Dist: big_o>=0.10.1; extra == "testing"
Requires-Dist: twine>=3.1.1; extra == "testing"
Requires-Dist: pydot; extra == "testing"
Requires-Dist: pytest>=5.2.0; extra == "testing"
Requires-Dist: check-manifest>=0.41; extra == "testing"
Requires-Dist: pre-commit; extra == "testing"
Requires-Dist: pytest-spark>=0.6.0; extra == "testing"
Requires-Dist: pyarrow>=1.0.1; extra == "testing"
Requires-Dist: numba; extra == "testing"
Requires-Dist: pyspark; extra == "testing"
Provides-Extra: dev
Requires-Dist: visions[plotting,testing]; extra == "dev"
Provides-Extra: all
Requires-Dist: visions[plotting,type_geometry,type_image_path]; extra == "all"
